smbus2/__init__.py
smbus2/smbus.py
reverb_i2c-1.1.1.dist-info/METADATA
reverb_i2c-1.1.1.dist-info/WHEEL
reverb_i2c-1.1.1.dist-info/top_level.txt
reverb_i2c-1.1.1.dist-info/RECORD
